acai_aws/__init__.py
acai_aws/apigateway/__init__.py
acai_aws/apigateway/__main__.py
acai_aws/apigateway/config_validator.py
acai_aws/apigateway/endpoint.py
acai_aws/apigateway/exception.py
acai_aws/apigateway/request.py
acai_aws/apigateway/requirements.py
acai_aws/apigateway/response.py
acai_aws/apigateway/router.py
acai_aws/apigateway/resolver/__init__.py
acai_aws/apigateway/resolver/cache.py
acai_aws/apigateway/resolver/importer.py
acai_aws/apigateway/resolver/modes/__init__.py
acai_aws/apigateway/resolver/modes/base.py
acai_aws/apigateway/resolver/modes/directory.py
acai_aws/apigateway/resolver/modes/mapping.py
acai_aws/apigateway/resolver/modes/pattern.py
acai_aws/base/__init__.py
acai_aws/base/event.py
acai_aws/base/no_data.py
acai_aws/base/placeholder.py
acai_aws/base/record.py
acai_aws/common/__init__.py
acai_aws/common/json_helper.py
acai_aws/common/schema.py
acai_aws/common/validator.py
acai_aws/common/logger/__init__.py
acai_aws/common/logger/common_logger.py
acai_aws/common/logger/decorator.py
acai_aws/common/records/__init__.py
acai_aws/common/records/event.py
acai_aws/common/records/exception.py
acai_aws/common/records/record.py
acai_aws/common/records/requirements.py
acai_aws/documentdb/__init__.py
acai_aws/documentdb/event.py
acai_aws/documentdb/record.py
acai_aws/documentdb/requirements.py
acai_aws/dynamodb/__init__.py
acai_aws/dynamodb/event.py
acai_aws/dynamodb/record.py
acai_aws/dynamodb/requirements.py
acai_aws/firehose/__init__.py
acai_aws/firehose/event.py
acai_aws/firehose/record.py
acai_aws/firehose/requirements.py
acai_aws/generic/__init__.py
acai_aws/generic/event.py
acai_aws/generic/requirements.py
acai_aws/kinesis/__init__.py
acai_aws/kinesis/event.py
acai_aws/kinesis/record.py
acai_aws/kinesis/requirements.py
acai_aws/mq/__init__.py
acai_aws/mq/event.py
acai_aws/mq/record.py
acai_aws/mq/requirements.py
acai_aws/msk/__init__.py
acai_aws/msk/event.py
acai_aws/msk/record.py
acai_aws/msk/requirements.py
acai_aws/s3/__init__.py
acai_aws-2.3.1.dist-info/licenses/LICENSE
acai_aws-2.3.1.dist-info/METADATA
acai_aws-2.3.1.dist-info/WHEEL
acai_aws-2.3.1.dist-info/top_level.txt
acai_aws-2.3.1.dist-info/RECORD
