Metadata-Version: 2.4
Name: acai_aws
Version: 2.3.1
Summary: DRY, configurable, declarative framework for building AWS Lambda APIs and event processors
Home-page: https://github.com/syngenta/acai-python
Author: Paul Cruse III
Author-email: paulcruse3@gmail.com
License: Apache 2.0
Project-URL: Homepage, https://github.com/syngenta/acai-python
Project-URL: Documentation, https://syngenta.github.io/acai-python-docs/
Project-URL: Source, https://github.com/syngenta/acai-python
Project-URL: Issue Tracker, https://github.com/syngenta/acai-python/issues
Project-URL: CI/CD, https://circleci.com/gh/syngenta/acai-python
Keywords: aws,lambda,serverless,apigateway,router,openapi,pydantic,dynamodb,sqs,sns,s3,kinesis,firehose,msk,documentdb,event-driven,validation,jsonschema,python-framework
Platform: any
Classifier: Development Status :: 5 - Production/Stable
Classifier: Intended Audience :: Developers
Classifier: Intended Audience :: Information Technology
Classifier: License :: OSI Approved :: Apache Software License
Classifier: Environment :: Web Environment
Classifier: Environment :: Console
Classifier: Operating System :: OS Independent
Classifier: Programming Language :: Python
Classifier: Programming Language :: Python :: 3
Classifier: Programming Language :: Python :: 3.8
Classifier: Programming Language :: Python :: 3.9
Classifier: Programming Language :: Python :: 3.10
Classifier: Programming Language :: Python :: 3.11
Classifier: Programming Language :: Python :: 3.12
Classifier: Topic :: Internet :: WWW/HTTP :: Dynamic Content
Classifier: Topic :: Software Development :: Libraries :: Python Modules
Classifier: Topic :: Software Development :: Libraries :: Application Frameworks
Classifier: Topic :: System :: Distributed Computing
Classifier: Topic :: System :: Monitoring
Classifier: Natural Language :: English
Requires-Python: >=3.8
License-File: LICENSE
Requires-Dist: boto3
Requires-Dist: dynamodb_json
Requires-Dist: jsonpickle
Requires-Dist: jsonref
Requires-Dist: jsonschema
Requires-Dist: icecream
Requires-Dist: pydantic
Requires-Dist: pyyaml
Requires-Dist: simplejson
Requires-Dist: xmltodict
Dynamic: author
Dynamic: author-email
Dynamic: classifier
Dynamic: description
Dynamic: description-content-type
Dynamic: home-page
Dynamic: keywords
Dynamic: license
Dynamic: license-file
Dynamic: platform
Dynamic: project-url
Dynamic: requires-dist
Dynamic: requires-python
Dynamic: summary
